retrigen/__init__.py
retrigen/filter_text.py
retrigen-0.1.1.dist-info/LICENSE
retrigen-0.1.1.dist-info/METADATA
retrigen-0.1.1.dist-info/WHEEL
retrigen-0.1.1.dist-info/top_level.txt
retrigen-0.1.1.dist-info/RECORD
