Metadata-Version: 2.1
Name: retrigen
Version: 0.1.1
Summary: A package for automatically generating datasets for training or evaluating retrieval models
Author: Jesper Alkestrup
Author-email: Kenneth Enevoldsen <Kenneth.enevoldsen@cas.au.dk>
License: MIT License
Project-URL: homepage, https://github.com/KennethEnevoldsen/retrigen
Project-URL: repository, https://github.com/KennethEnevoldsen/retrigen
Project-URL: documentation, https://KennethEnevoldsen.github.io/retrigen/
Classifier: Operating System :: POSIX :: Linux
Classifier: Operating System :: MacOS :: MacOS X
Classifier: Operating System :: Microsoft :: Windows
Classifier: Programming Language :: Python :: 3.9
Classifier: Programming Language :: Python :: 3.10
Classifier: Programming Language :: Python :: 3.11
Classifier: Programming Language :: Python :: 3.12
Requires-Python: >=3.9
License-File: LICENSE
Requires-Dist: openai
Requires-Dist: tqdm
Requires-Dist: langchain
Requires-Dist: textdescriptives
Requires-Dist: spacy >3.6.0
Requires-Dist: chromadb
Provides-Extra: dev
Requires-Dist: cruft >=2.0.0 ; extra == 'dev'
Requires-Dist: pyright >=1.1.338 ; extra == 'dev'
Requires-Dist: ruff >=0.3.0 ; extra == 'dev'
Requires-Dist: pyproject-parser[cli,readme] >=0.9.1 ; extra == 'dev'
Provides-Extra: docs
Requires-Dist: mkdocs-jupyter ==0.24.2 ; extra == 'docs'
Requires-Dist: mkdocs-material ==9.1.21 ; extra == 'docs'
Requires-Dist: mkdocstrings[python] ==0.22.0 ; extra == 'docs'
Requires-Dist: jupyter >=1.0.0 ; extra == 'docs'
Provides-Extra: tests
Requires-Dist: pytest >=7.1.3 ; extra == 'tests'
Requires-Dist: pytest-cov >=3.0.0 ; extra == 'tests'
Requires-Dist: pytest-xdist ; extra == 'tests'
